README.rst
setup.py
bin/multicerti
multicerti/__init__.py
multicerti/app.py
multicerti/conf.py
multicerti/nginxparser.py
multicerti/to_tempfile.py
multicerti/virtualhost.py
multicerti.egg-info/PKG-INFO
multicerti.egg-info/SOURCES.txt
multicerti.egg-info/dependency_links.txt
multicerti.egg-info/requires.txt
multicerti.egg-info/top_level.txt