Metadata-Version: 1.2
Name: multicerti
Version: 0.1.0
Summary: Quickly obtain or renew Letsencrypt ssl certificates for multiple domains. Automatically configure Nginx as a https frontend and http reverse proxy for these.
Home-page: UNKNOWN
Author: Benjamin Le Forestier
Author-email: benjamin@leforestier.org
License: UNKNOWN
Keywords: letsencrypt,let's encrypt,certbot,reverse proxy,ssl,tls,certificate,http,https,proxy
Platform: UNKNOWN
Classifier: Intended Audience :: System Administrators
Classifier: Intended Audience :: Developers
Classifier: License :: OSI Approved :: BSD License
Classifier: Programming Language :: Python
Classifier: Programming Language :: Python :: 3
Classifier: Programming Language :: Python :: 3.3
Classifier: Programming Language :: Python :: 3.4
Classifier: Programming Language :: Python :: 3.5
Classifier: Programming Language :: Python :: 3.6
Classifier: Topic :: Internet :: Proxy Servers
Classifier: Topic :: Internet :: WWW/HTTP :: HTTP Servers
Classifier: Topic :: Internet :: WWW/HTTP :: Site Management
Classifier: Topic :: Security :: Cryptography
Classifier: Operating System :: Unix
Requires-Python: >=3.3
